bdclient/__init__.py
bdclient/py.typed
bdclient/scraper/__init__.py
bdclient/scraper/base/__init__.py
bdclient/scraper/base/collect.py
bdclient/scraper/base/discovery.py
bdclient/scraper/base/polling.py
bdclient/scraper/google_news.py
bdclient/scraper/google_serp.py
bdclient/scraper/youtube_videos.py
bdclient/serp/__init__.py
bdclient/serp/google_search.py
bdclient/unlocker.py
bdclient-0.4.2.dist-info/WHEEL
bdclient-0.4.2.dist-info/METADATA
bdclient-0.4.2.dist-info/RECORD
