Metadata-Version: 2.3
Name: bdclient
Version: 0.4.2
Summary: An unofficial Python client for Bright Data APIs.
Requires-Dist: httpx>=0.28.1
Requires-Dist: pydantic>=2.11.9
Requires-Dist: pydantic-settings>=2.11.0
Requires-Python: >=3.12
